sudregex/__init__.py
sudregex/checklist.py
sudregex/cli.py
sudregex/helper.py
sudregex/termslist.py
sudregex/validation.py
sudregex-0.1.2.dist-info/licenses/LICENSE
sudregex-0.1.2.dist-info/METADATA
sudregex-0.1.2.dist-info/WHEEL
sudregex-0.1.2.dist-info/entry_points.txt
sudregex-0.1.2.dist-info/top_level.txt
sudregex-0.1.2.dist-info/RECORD
