Metadata-Version: 2.4
Name: sudregex
Version: 0.1.2
Summary: Regex-driven extraction with negation for clinical text (SUD-focused).
Author-email: Quantitative Nurse Lab <quantitativenurse@gmail.com>
License: MIT
Project-URL: Homepage, https://github.com/quantitativenurse/sud-regex
Project-URL: Issues, https://github.com/quantitativenurse/sud-regex/issues
Classifier: Development Status :: 3 - Alpha
Classifier: Intended Audience :: Science/Research
Classifier: License :: OSI Approved :: MIT License
Classifier: Programming Language :: Python :: 3
Classifier: Programming Language :: Python :: 3 :: Only
Classifier: Programming Language :: Python :: 3.9
Classifier: Programming Language :: Python :: 3.10
Classifier: Programming Language :: Python :: 3.11
Classifier: Programming Language :: Python :: 3.12
Classifier: Topic :: Scientific/Engineering :: Information Analysis
Classifier: Operating System :: OS Independent
Requires-Python: >=3.9
License-File: LICENSE
Requires-Dist: pandas>=1.5
Requires-Dist: numpy>=1.21
Provides-Extra: dev
Requires-Dist: black==25.1.0; extra == "dev"
Requires-Dist: flake8==7.3.0; extra == "dev"
Requires-Dist: isort==6.0.1; extra == "dev"
Requires-Dist: pytest; extra == "dev"
Requires-Dist: build; extra == "dev"
Requires-Dist: twine; extra == "dev"
Provides-Extra: viz
Requires-Dist: matplotlib>=3.6; extra == "viz"
Provides-Extra: yaml
Requires-Dist: pyyaml>=6; extra == "yaml"
Provides-Extra: parallel
Requires-Dist: pandarallel>=1.6; extra == "parallel"
Provides-Extra: all
Requires-Dist: matplotlib>=3.6; extra == "all"
Requires-Dist: pyyaml>=6; extra == "all"
Requires-Dist: pandarallel>=1.6; extra == "all"
Dynamic: license-file
